tflibrosa/__init__.py
tflibrosa/stft.py
tflibrosa-0.0.2.dist-info/LICENSE
tflibrosa-0.0.2.dist-info/METADATA
tflibrosa-0.0.2.dist-info/WHEEL
tflibrosa-0.0.2.dist-info/top_level.txt
tflibrosa-0.0.2.dist-info/RECORD
