Metadata-Version: 2.1
Name: tflibrosa
Version: 0.0.2
Summary: Re-implementation of some librosa function for tensorflow. Reproduction from torchlibrosa.
Home-page: https://github.com/Shiro-LK/tflibrosa
Download-URL: https://github.com/Shiro-LK/tflibrosa.git
Author: Shiro-LK
Author-email: shirosaki94@gmail.com
License: MIT License
Keywords: tflibrosa,tensorflow,librosa
Classifier: Development Status :: 5 - Production/Stable
Classifier: Programming Language :: Python :: 3.7
Classifier: Programming Language :: Python :: 3.8
License-File: LICENSE
Requires-Dist: numpy
Requires-Dist: pytest
Requires-Dist: tensorflow
Requires-Dist: librosa
